README.rst
setup.py
compound_word_splitter.egg-info/PKG-INFO
compound_word_splitter.egg-info/SOURCES.txt
compound_word_splitter.egg-info/dependency_links.txt
compound_word_splitter.egg-info/not-zip-safe
compound_word_splitter.egg-info/top_level.txt
splitter/__init__.py
splitter/compound_word_splitter.py