Metadata-Version: 1.1
Name: compound-word-splitter
Version: 0.4
Summary: Splits compound words, like German "Effektivitätsberechnung
Home-page: https://github.com/TimKam/compound-word-splitter
Author: Timotheus Kampik
Author-email: timotheus.kampik@gmail.com
License: MIT
Platform: any
Classifier: Development Status :: 4 - Beta
Classifier: Operating System :: OS Independent
Classifier: Programming Language :: Python
Classifier: Environment :: Plugins
Classifier: Intended Audience :: Developers
Classifier: License :: OSI Approved :: MIT License
Classifier: Topic :: Documentation
